uvicorn_zero_copy/__init__.py
uvicorn_zero_copy/py.typed
uvicorn_zero_copy-0.0.0.dist-info/METADATA
uvicorn_zero_copy-0.0.0.dist-info/WHEEL
uvicorn_zero_copy-0.0.0.dist-info/RECORD
