Metadata-Version: 2.1
Name: uvicorn-zero-copy
Version: 0.0.0
Summary: Uvicorn with Zero-Copy Send extension!
Author-email: Marcelo Trylesinski <marcelotryle@gmail.com>
License: MIT
